controller/__init__.py
controller/__main__.py
controller/app.py
controller/packages.py
controller/project.py
controller/py.typed
controller/templating.py
controller/builds/backend/gunicorn_conf.py
controller/builds/backend-legacy310/gunicorn_conf.py
controller/builds/backend-legacy39/gunicorn_conf.py
controller/commands/__init__.py
controller/commands/add.py
controller/commands/backup.py
controller/commands/build.py
controller/commands/check.py
controller/commands/create.py
controller/commands/dump.py
controller/commands/init.py
controller/commands/install.py
controller/commands/interfaces.py
controller/commands/list.py
controller/commands/password.py
controller/commands/pull.py
controller/commands/reload.py
controller/commands/restart.py
controller/commands/restore.py
controller/commands/run.py
controller/commands/shell.py
controller/commands/ssl.py
controller/commands/start.py
controller/commands/status.py
controller/commands/tuning.py
controller/commands/update.py
controller/commands/upgrade.py
controller/commands/version.py
controller/commands/volatile.py
controller/commands/backup_modules/__init__.py
controller/commands/backup_modules/neo4j.py
controller/commands/backup_modules/postgres.py
controller/commands/backup_modules/rabbit.py
controller/commands/backup_modules/redis.py
controller/commands/compose/__init__.py
controller/commands/compose/logs.py
controller/commands/compose/remove.py
controller/commands/compose/scale.py
controller/commands/compose/stop.py
controller/commands/password_modules/__init__.py
controller/commands/password_modules/backend.py
controller/commands/password_modules/flower.py
controller/commands/password_modules/neo4j.py
controller/commands/password_modules/postgres.py
controller/commands/password_modules/rabbit.py
controller/commands/password_modules/redis.py
controller/commands/password_modules/registry.py
controller/commands/restore_modules/__init__.py
controller/commands/restore_modules/neo4j.py
rapydo-3.0.dist-info/LICENSE
rapydo-3.0.dist-info/METADATA
rapydo-3.0.dist-info/WHEEL
rapydo-3.0.dist-info/entry_points.txt
rapydo-3.0.dist-info/top_level.txt
rapydo-3.0.dist-info/RECORD
