Metadata-Version: 2.1
Name: rapydo
Version: 3.0
Summary: Manage and deploy projects based on RAPyDo framework
License: MIT License
Project-URL: homepage, https://rapydo.github.io/docs
Project-URL: documentation, https://do.readthedocs.io
Project-URL: repository, https://github.com/rapydo/do
Keywords: http,api,rest,docker,docker-compose,docker-swarm,rapydo
Classifier: Programming Language :: Python
Classifier: Intended Audience :: Developers
Classifier: Development Status :: 5 - Production/Stable
Classifier: License :: OSI Approved :: MIT License
Classifier: Programming Language :: Python :: 3.8
Classifier: Programming Language :: Python :: 3.9
Classifier: Programming Language :: Python :: 3.10
Classifier: Programming Language :: Python :: 3.11
Classifier: Programming Language :: Python :: 3.12
Requires-Python: >=3.8
License-File: LICENSE
Requires-Dist: python-on-whales ==0.70.1
Requires-Dist: python-dateutil
Requires-Dist: pytz
Requires-Dist: loguru
Requires-Dist: jinja2
Requires-Dist: sultan ==0.9.1
Requires-Dist: plumbum
Requires-Dist: glom
Requires-Dist: GitPython ==3.1.43
Requires-Dist: PyYAML ==6.0.1
Requires-Dist: pydantic ==2.7.0
Requires-Dist: pip ==24.0
Requires-Dist: setuptools ==69.2.0
Requires-Dist: wheel ==0.43.0
Requires-Dist: requests ==2.31.0
Requires-Dist: typer[all] ==0.9.0
Requires-Dist: click ==8.1.7
Requires-Dist: zxcvbn
Requires-Dist: packaging
Provides-Extra: dev
Requires-Dist: pytest ==8.1.1 ; extra == 'dev'
Requires-Dist: pytest-cov ==5.0.0 ; extra == 'dev'
Requires-Dist: pytest-sugar ==1.0.0 ; extra == 'dev'
Requires-Dist: pytest-timeout ==2.3.1 ; extra == 'dev'
Requires-Dist: freezegun ==1.4.0 ; extra == 'dev'
Requires-Dist: Faker ; extra == 'dev'
Provides-Extra: types
Requires-Dist: rapydo[dev] ; extra == 'types'
Requires-Dist: mypy ==1.9.0 ; extra == 'types'
Requires-Dist: lxml ==5.2.1 ; extra == 'types'
Requires-Dist: html5lib ==1.1 ; extra == 'types'
Requires-Dist: types-PyYAML ==6.0.12.20240311 ; extra == 'types'
Requires-Dist: types-python-dateutil ==2.9.0.20240316 ; extra == 'types'
Requires-Dist: types-pytz ==2024.1.0.20240203 ; extra == 'types'
Requires-Dist: types-requests ==2.31.0.20240406 ; extra == 'types'
Requires-Dist: types-freezegun ==1.1.10 ; extra == 'types'
